LICENSE
README.md
pyproject.toml
setup.py
tests/__init__.py
tests/test_api.py
upchatpy/__init__.py
upchatpy/api.py
upchatpy/exceptions.py
upchatpy/version.py
upchatpy.egg-info/PKG-INFO
upchatpy.egg-info/SOURCES.txt
upchatpy.egg-info/dependency_links.txt
upchatpy.egg-info/requires.txt
upchatpy.egg-info/top_level.txt
upchatpy/responses/__init__.py
upchatpy/responses/auth.py
upchatpy/responses/enums.py
upchatpy/responses/orders.py
upchatpy/responses/products.py
upchatpy/responses/users.py
upchatpy/responses/webhooks.py