Metadata-Version: 2.1
Name: upchatpy
Version: 1.1.5
Summary: A type hinted async Python wrapper for the Upgrade.Chat API
Home-page: https://github.com/vertyco/upchatpy
Author: vertyco
Author-email: alex.c.goble@gmail.com
Project-URL: Changelog, https://github.com/vertyco/upchatpy/blob/main/CHANGELOG.md
Keywords: Upgrade.Chat,chat,bot,discord,upgradechat,donations,subscriptions,monetization,payment,api,wrapper,client
Classifier: Development Status :: 5 - Production/Stable
Classifier: License :: OSI Approved :: MIT License
Classifier: Intended Audience :: Developers
Classifier: Operating System :: OS Independent
Classifier: Natural Language :: English
Classifier: Programming Language :: Python :: 3
Classifier: Programming Language :: Python :: 3.8
Classifier: Programming Language :: Python :: 3.9
Classifier: Programming Language :: Python :: 3.10
Classifier: Programming Language :: Python :: 3.11
Classifier: Programming Language :: Python :: 3.12
Classifier: Framework :: Pydantic :: 1
Classifier: Framework :: Pydantic :: 2
Classifier: Topic :: Internet
Classifier: Topic :: Software Development :: Libraries
Classifier: Topic :: Software Development :: Libraries :: Python Modules
Classifier: Topic :: Utilities
Classifier: Typing :: Typed
Requires-Python: >=3.8
License-File: LICENSE
